{
  "$schema": "https://developer.microsoft.com/json-schemas/fabric/item/report/definition/visualContainer/2.4.0/schema.json",
  "name": "9bb172b6a23707dc0e0d",
  "position": {
    "x": 480,
    "y": 576,
    "z": 11000,
    "height": 432,
    "width": 703.99999999999989,
    "tabOrder": 4000
  },
  "visual": {
    "visualType": "areaChart",
    "query": {
      "queryState": {
        "Category": {
          "projections": [
            {
              "field": {
                "HierarchyLevel": {
                  "Expression": {
                    "Hierarchy": {
                      "Expression": {
                        "SourceRef": {
                          "Entity": "DateTable"
                        }
                      },
                      "Hierarchy": "Date Hierarchy"
                    }
                  },
                  "Level": "Year"
                }
              },
              "queryRef": "DateTable.Date Hierarchy.Year",
              "nativeQueryRef": "Date Hierarchy Year",
              "active": true
            },
            {
              "field": {
                "HierarchyLevel": {
                  "Expression": {
                    "Hierarchy": {
                      "Expression": {
                        "SourceRef": {
                          "Entity": "DateTable"
                        }
                      },
                      "Hierarchy": "Date Hierarchy"
                    }
                  },
                  "Level": "Month"
                }
              },
              "queryRef": "DateTable.Date Hierarchy.Month",
              "nativeQueryRef": "Date Hierarchy Month",
              "active": true
            }
          ],
          "showAll": true
        },
        "Y": {
          "projections": [
            {
              "field": {
                "Aggregation": {
                  "Expression": {
                    "Column": {
                      "Expression": {
                        "SourceRef": {
                          "Entity": "EXAMPLE - Projects"
                        }
                      },
                      "Property": "Project ID"
                    }
                  },
                  "Function": 5
                }
              },
              "queryRef": "CountNonNull(EXAMPLE - Projects.Project ID)",
              "nativeQueryRef": "Number of Projects",
              "displayName": "Number of Projects"
            }
          ]
        }
      },
      "sortDefinition": {
        "sort": [
          {
            "field": {
              "HierarchyLevel": {
                "Expression": {
                  "Hierarchy": {
                    "Expression": {
                      "SourceRef": {
                        "Entity": "DateTable"
                      }
                    },
                    "Hierarchy": "Date Hierarchy"
                  }
                },
                "Level": "Year"
              }
            },
            "direction": "Ascending"
          },
          {
            "field": {
              "HierarchyLevel": {
                "Expression": {
                  "Hierarchy": {
                    "Expression": {
                      "SourceRef": {
                        "Entity": "DateTable"
                      }
                    },
                    "Hierarchy": "Date Hierarchy"
                  }
                },
                "Level": "Month"
              }
            },
            "direction": "Ascending"
          }
        ]
      }
    },
    "objects": {
      "labels": [
        {
          "properties": {
            "show": {
              "expr": {
                "Literal": {
                  "Value": "true"
                }
              }
            },
            "labelPosition": {
              "expr": {
                "Literal": {
                  "Value": "'Auto'"
                }
              }
            }
          }
        }
      ],
      "valueAxis": [
        {
          "properties": {
            "titleBold": {
              "expr": {
                "Literal": {
                  "Value": "true"
                }
              }
            },
            "show": {
              "expr": {
                "Literal": {
                  "Value": "true"
                }
              }
            },
            "showAxisTitle": {
              "expr": {
                "Literal": {
                  "Value": "true"
                }
              }
            },
            "start": {
              "expr": {
                "Literal": {
                  "Value": "0D"
                }
              }
            }
          }
        }
      ],
      "categoryAxis": [
        {
          "properties": {
            "titleBold": {
              "expr": {
                "Literal": {
                  "Value": "true"
                }
              }
            },
            "showAxisTitle": {
              "expr": {
                "Literal": {
                  "Value": "true"
                }
              }
            },
            "concatenateLabels": {
              "expr": {
                "Literal": {
                  "Value": "false"
                }
              }
            },
            "titleText": {
              "expr": {
                "Literal": {
                  "Value": "'Month and Year'"
                }
              }
            }
          }
        }
      ],
      "lineStyles": [
        {
          "properties": {
            "showMarker": {
              "expr": {
                "Literal": {
                  "Value": "true"
                }
              }
            }
          }
        }
      ]
    },
    "visualContainerObjects": {
      "title": [
        {
          "properties": {
            "text": {
              "expr": {
                "Literal": {
                  "Value": "'Projects Completed by Month and Year'"
                }
              }
            }
          }
        }
      ],
      "general": [
        {
          "properties": {
            "altText": {
              "expr": {
                "Literal": {
                  "Value": "'Shows the number of projects that fall into the different Effort Health categories.'"
                }
              }
            }
          }
        }
      ]
    },
    "drillFilterOtherVisuals": true
  },
  "filterConfig": {
    "filters": [
      {
        "name": "587e49980614ed369ae3",
        "field": {
          "Column": {
            "Expression": {
              "SourceRef": {
                "Entity": "DateTable"
              }
            },
            "Property": "Date"
          }
        },
        "type": "RelativeDate",
        "filter": {
          "Version": 2,
          "From": [
            {
              "Name": "d",
              "Entity": "DateTable",
              "Type": 0
            }
          ],
          "Where": [
            {
              "Condition": {
                "Between": {
                  "Expression": {
                    "Column": {
                      "Expression": {
                        "SourceRef": {
                          "Source": "d"
                        }
                      },
                      "Property": "Date"
                    }
                  },
                  "LowerBound": {
                    "DateSpan": {
                      "Expression": {
                        "DateAdd": {
                          "Expression": {
                            "DateAdd": {
                              "Expression": {
                                "Now": {}
                              },
                              "Amount": 1,
                              "TimeUnit": 0
                            }
                          },
                          "Amount": -1000,
                          "TimeUnit": 2
                        }
                      },
                      "TimeUnit": 0
                    }
                  },
                  "UpperBound": {
                    "DateSpan": {
                      "Expression": {
                        "Now": {}
                      },
                      "TimeUnit": 0
                    }
                  }
                }
              }
            }
          ]
        },
        "howCreated": "User"
      },
      {
        "name": "3e46d6a55d200c1cb061",
        "field": {
          "Column": {
            "Expression": {
              "SourceRef": {
                "Entity": "DateTable"
              }
            },
            "Property": "Date"
          }
        },
        "type": "Advanced",
        "filter": {
          "Version": 2,
          "From": [
            {
              "Name": "d",
              "Entity": "DateTable",
              "Type": 0
            }
          ],
          "Where": [
            {
              "Condition": {
                "Comparison": {
                  "ComparisonKind": 2,
                  "Left": {
                    "Column": {
                      "Expression": {
                        "SourceRef": {
                          "Source": "d"
                        }
                      },
                      "Property": "Date"
                    }
                  },
                  "Right": {
                    "DateSpan": {
                      "Expression": {
                        "Literal": {
                          "Value": "datetime'2024-08-01T00:00:00'"
                        }
                      },
                      "TimeUnit": 5
                    }
                  }
                }
              }
            }
          ]
        },
        "howCreated": "User"
      }
    ]
  }
}